quick_pypi/__init__.py
quick_pypi/deploy.py
quick_pypi/deploy_toml.py
quick_pypi/__pycache__/__init__.cpython-36.pyc
quick_pypi/__pycache__/deploy.cpython-36.pyc
quick_pypi/template/LICENSE
quick_pypi/template/MANIFEST.in
quick_pypi/template/README.md
quick_pypi/template/pyproject.toml
quick_pypi/template/pyproject_no_urls.toml
quick_pypi/template/pyproject_only_project_url.toml
quick_pypi/template/setup.cfg
quick_pypi/template/setup.py
quick_pypi/template/setup_no_urls.py
quick_pypi/template/setup_with_only_project_url.py
quick_pypi-0.0.4.dist-info/LICENSE
quick_pypi-0.0.4.dist-info/METADATA
quick_pypi-0.0.4.dist-info/WHEEL
quick_pypi-0.0.4.dist-info/top_level.txt
quick_pypi-0.0.4.dist-info/RECORD
